4.DSD/WEEK2/W2P3.v
module W2P3(x1,x2,x3,x4,f);
input x1,x2,x3,x4;
output f;
and(k1,x2,x3);
and(k2,k1,x4);
and(k3,x1,x3);
and(k4,k3,x4);
and(k5,x1,x2);
and(k6,k5,x4);
and(k7,x1,x2);
and(k8,k7,x3);
or(k9,k4,k2);
or(k10,k6,k8);
or(f,k10,k9);
endmodule

DSD/WEEK2/W2P3_tb.v
`timescale 1ns/1ns
`include "W2P3.v"
module W2P3_tb;
reg x1,x2,x3,x4;
wire f;
W2P3 uut(x1,x2,x3,x4,f);
initial begin
        $dumpfile("W2P3_tb.vcd");
        $dumpvars(0,W2P3_tb);
             
        x1=0;
        x2=0;
        x3=0;
        x4=0;
        #20;
             
        x1=0;
        x2=0;
        x3=0;
        x4=1;
        #20;
             
        x1=0;
        x2=0;
        x3=1;
        x4=0;
        #20;
             
        x1=0;
        x2=0;
        x3=1;
        x4=1;
        #20;
        
        x1=0;
        x2=1;
        x3=0;
        x4=0;
        #20;
        
        x1=0;
        x2=1;
        x3=0;
        x4=1;
        #20;
             
        x1=0;
        x2=1;
        x3=1;
        x4=0;
        #20;
             
        x1=0;
        x2=1;
        x3=1;
        x4=1;
        #20;
        
        x1=1;
        x2=0;
        x3=0;
        x4=0;
        #20;
        
        x1=1;
        x2=0;
        x3=0;
        x4=1;
        #20;
        
        x1=1;
        x2=0;
        x3=1;
        x4=0;
        #20;
        
        x1=1;
        x2=0;
        x3=1;
        x4=1;
        #20;
        
        x1=1;
        x2=1;
        x3=0;
        x4=0;
        #20;
        
        x1=1;
        x2=1;
        x3=0;
        x4=1;
        #20;
        
        x1=1;
        x2=1;
        x3=1;
        x4=0;
        #20;
        
        x1=1;
        x2=1;
        x3=1;
        x4=1;
        #20;
             
             
        $display("Test complete");
end
endmodule

4.DSD/WEEK2/W2P3_tb.vcd
$date
	Wed Sep 21 16:20:18 2022
$end
$version
	Icarus Verilog
$end
$timescale
	1ns
$end
$scope module W2P3_tb $end
$var wire 1 ! f $end
$var reg 1 " x1 $end
$var reg 1 # x2 $end
$var reg 1 $ x3 $end
$var reg 1 % x4 $end
$scope module uut $end
$var wire 1 ! f $end
$var wire 1 & k1 $end
$var wire 1 ' k10 $end
$var wire 1 ( k2 $end
$var wire 1 ) k3 $end
$var wire 1 * k4 $end
$var wire 1 + k5 $end
$var wire 1 , k6 $end
$var wire 1 - k7 $end
$var wire 1 . k8 $end
$var wire 1 / k9 $end
$var wire 1 " x1 $end
$var wire 1 # x2 $end
$var wire 1 $ x3 $end
$var wire 1 % x4 $end
$upscope $end
$upscope $end
$enddefinitions $end
#0
$dumpvars
0/
0.
0-
0,
0+
0*
0)
0(
0'
0&
0%
0$
0#
0"
0!
$end
#20
1%
#40
0%
1$
#60
1%
#80
0%
0$
1#
#100
1%
#120
1&
0%
1$
#140
1!
1/
1(
1%
#160
0!
0/
0(
0&
0%
0$
0#
1"
#180
1%
#200
1)
0%
1$
#220
1!
1/
1*
1%
#240
0!
0/
0*
0)
1+
1-
0%
0$
1#
#260
1!
1'
1,
1%
#280
0,
1&
1)
1.
0%
1$
#300
1/
1(
1*
1,
1%
