4.DSD/WEEK8/W8P3.v
// 4 To 16 Decoder using 2 To 4 Decoder
// 2 to 4 Decoder is using case statement
module W8P3(w,En,y);
    input [3:0] w;
    input En;
    output [0:15] y;
    wire [0:3] y2;
    
    TwoToFourDecoder stage0(w[3:2],En,y2);
    TwoToFourDecoder stage1(w[1:0],y2[0],y[0:3]);
    TwoToFourDecoder stage2(w[1:0],y2[1],y[4:7]);
    TwoToFourDecoder stage3(w[1:0],y2[2],y[8:11]);
    TwoToFourDecoder stage4(w[1:0],y2[3],y[12:15]);

endmodule

module TwoToFourDecoder(w,En,y);
    input [1:0] w;
    input En;
    output reg [0:3] y;
    always @(w or En)
    begin
            y=4'b0000;
        if (En == 1)
        begin
            case(w)
            0:  y[0] = 1;
            1:  y[1] = 1;
            2:  y[2] = 1;
            3:  y[3] = 1; 
            endcase
        end
    end
endmodule

/*
module TwoToFourDecoder(w,En,y);
    input [1:0] w;
    input En;
    output reg [0:3] y;
    integer k;
    always @(w or En)
    for (k = 0; k <= 3; k=k+1)
        if ((w==k) && (En == 1))
            y[k] = 1;
        else
            y[k] = 0;
endmodule */

4.DSD/WEEK8/W8P3_tb.v
`timescale 1ns/1ns
`include "W8P3.v"

module W8P3_tb();
reg [3:0] w;
reg En;
wire [0:15] y;

W8P3 q(w,En,y);
initial
begin
    $dumpfile("W8P3_tb.vcd");
    $dumpvars(0,W8P3_tb);

    w = 4'b0000; En = 1; #20;
    w = 4'b0001; En = 1; #20;
    w = 4'b0010; En = 1; #20;
    w = 4'b0011; En = 1; #20;
    w = 4'b0100; En = 1; #20;
    w = 4'b0101; En = 1; #20;
    w = 4'b0110; En = 1; #20;
    w = 4'b0111; En = 1; #20;
    w = 4'b1000; En = 1; #20;
    w = 4'b1001; En = 1; #20;
    w = 4'b1010; En = 1; #20;
    w = 4'b1011; En = 1; #20;
    w = 4'b1100; En = 1; #20;
    w = 4'b1101; En = 1; #20;
    w = 4'b1110; En = 1; #20;
    w = 4'b1111; En = 1; #20;

    $display("Test Complete");

end
endmodule

4.DSD/WEEK8/W8P3_tb.vcd
$date
	Thu Oct 20 09:15:46 2022
$end
$version
	Icarus Verilog
$end
$timescale
	1ns
$end
$scope module W8P3_tb $end
$var wire 16 ! y [0:15] $end
$var reg 1 " En $end
$var reg 4 # w [3:0] $end
$scope module q $end
$var wire 1 " En $end
$var wire 4 $ w [3:0] $end
$var wire 4 % y2 [0:3] $end
$var wire 16 & y [0:15] $end
$scope module stage0 $end
$var wire 1 " En $end
$var wire 2 ' w [1:0] $end
$var reg 4 ( y [0:3] $end
$upscope $end
$scope module stage1 $end
$var wire 1 ) En $end
$var wire 2 * w [1:0] $end
$var reg 4 + y [0:3] $end
$upscope $end
$scope module stage2 $end
$var wire 1 , En $end
$var wire 2 - w [1:0] $end
$var reg 4 . y [0:3] $end
$upscope $end
$scope module stage3 $end
$var wire 1 / En $end
$var wire 2 0 w [1:0] $end
$var reg 4 1 y [0:3] $end
$upscope $end
$scope module stage4 $end
$var wire 1 2 En $end
$var wire 2 3 w [1:0] $end
$var reg 4 4 y [0:3] $end
$upscope $end
$upscope $end
$upscope $end
$enddefinitions $end
#0
$dumpvars
b0 4
b0 3
02
b0 1
b0 0
0/
b0 .
b0 -
0,
b1000 +
b0 *
1)
b1000 (
b0 '
b1000000000000000 &
b1000 %
b0 $
b0 #
1"
b1000000000000000 !
$end
#20
b100000000000000 !
b100000000000000 &
b100 +
b1 *
b1 -
b1 0
b1 3
b1 #
b1 $
#40
b10000000000000 !
b10000000000000 &
b10 +
b10 *
b10 -
b10 0
b10 3
b10 #
b10 $
#60
b1000000000000 !
b1000000000000 &
b1 +
b11 *
b11 -
b11 0
b11 3
b11 #
b11 $
#80
b1000 .
1,
0)
b100 %
b100 (
b100000000000 !
b100000000000 &
b0 +
b1 '
b0 *
b0 -
b0 0
b0 3
b100 #
b100 $
#100
b10000000000 !
b10000000000 &
b100 .
b1 *
b1 -
b1 0
b1 3
b101 #
b101 $
#120
b1000000000 !
b1000000000 &
b10 .
b10 *
b10 -
b10 0
b10 3
b110 #
b110 $
#140
b100000000 !
b100000000 &
b1 .
b11 *
b11 -
b11 0
b11 3
b111 #
b111 $
#160
b1000 1
1/
0,
b10 %
b10 (
b10000000 !
b10000000 &
b0 .
b10 '
b0 *
b0 -
b0 0
b0 3
b1000 #
b1000 $
#180
b1000000 !
b1000000 &
b100 1
b1 *
b1 -
b1 0
b1 3
b1001 #
b1001 $
#200
b100000 !
b100000 &
b10 1
b10 *
b10 -
b10 0
b10 3
b1010 #
b1010 $
#220
b10000 !
b10000 &
b1 1
b11 *
b11 -
b11 0
b11 3
b1011 #
b1011 $
#240
b1000 4
12
0/
b1 %
b1 (
b1000 !
b1000 &
b0 1
b11 '
b0 *
b0 -
b0 0
b0 3
b1100 #
b1100 $
#260
b100 !
b100 &
b100 4
b1 *
b1 -
b1 0
b1 3
b1101 #
b1101 $
#280
b10 !
b10 &
b10 4
b10 *
b10 -
b10 0
b10 3
b1110 #
b1110 $
#300
b1 !
b1 &
b1 4
b11 *
b11 -
b11 0
b11 3
b1111 #
b1111 $
