4.DSD/WEEK1/W1P1.v
module W1P1(a,b,c,d,f);
input a,b,c,d;
output f;
assign f=((~((a&b)|c))&d)&(((a&b)|c)|d);
endmodule

4.DSD/WEEK1/W1P1_tb.v
`timescale 1ns/1ns
`include "W1P1.v"
//Name of the Verilog file
module W1P1_tb();
reg a,b,c,d;
//Input
wire f;
//Output
W1P1 ex2(a,b,c,d, f); //Instantiation of the module
initial
begin
$dumpfile("W1P1_tb.vcd");
$dumpvars(0, W1P1_tb);
a=1'b0; b=1'b0; c=1'b0; d=1'b0;
#20;
a=1'b0; b=1'b0; c=1'b0; d=1'b1;
#20;
a=1'b0; b=1'b0; c=1'b1; d=1'b0;
#20;
a=1'b0; b=1'b0; c=1'b1; d=1'b1;
#20;
a=1'b0; b=1'b1; c=1'b0; d=1'b0;
#20;
a=1'b0; b=1'b1; c=1'b0; d=1'b1;
#20;
a=1'b0; b=1'b1; c=1'b1; d=1'b0;
#20;
a=1'b0; b=1'b1; c=1'b1; d=1'b1;
#20;
a=1'b1; b=1'b0; c=1'b0; d=1'b0;
#20;
a=1'b1; b=1'b0; c=1'b0; d=1'b1;
#20;
a=1'b1; b=1'b0; c=1'b1; d=1'b0;
#20;
a=1'b1; b=1'b0; c=1'b1; d=1'b1;
#20;
a=1'b1; b=1'b1; c=1'b0; d=1'b0;
#20;
a=1'b1; b=1'b1; c=1'b0; d=1'b1;
#20;
a=1'b1; b=1'b1; c=1'b1; d=1'b0;
#20;
a=1'b1; b=1'b1; c=1'b1; d=1'b1;
#20;
$display("Test complete");
end
endmodule

4.DSD/WEEK1/W1P1_tb.vcd
$date
	Wed Sep  7 15:31:15 2022
$end
$version
	Icarus Verilog
$end
$timescale
	1ns
$end
$scope module W1P1_tb $end
$var wire 1 ! f $end
$var reg 1 " a $end
$var reg 1 # b $end
$var reg 1 $ c $end
$var reg 1 % d $end
$scope module ex2 $end
$var wire 1 " a $end
$var wire 1 # b $end
$var wire 1 $ c $end
$var wire 1 % d $end
$var wire 1 ! f $end
$upscope $end
$upscope $end
$enddefinitions $end
#0
$dumpvars
0%
0$
0#
0"
0!
$end
#20
1!
1%
#40
0!
0%
1$
#60
1%
#80
0%
0$
1#
#100
1!
1%
#120
0!
0%
1$
#140
1%
#160
0%
0$
0#
1"
#180
1!
1%
#200
0!
0%
1$
#220
1%
#240
0%
0$
1#
#260
1%
#280
0%
1$
#300
1%
