4.DSD/WEEK4/W4P1B.v
module W4P1B(a,b,cin,s,cout);
	input a,b,cin;
	output s,cout;
	
	assign s = a ^ b ^ cin;
	assign cout = (a & b) | (a & cin) | (b & cin);
	
endmodule

DSD/WEEK4/W4P1B_tb.v
`timescale 1ns/1ns
`include "W4P1B.v"

module W4P1B_tb();
reg a,b,cin;
wire s,cout;

W4P1B fa(a,b,cin,s,cout);
initial 
begin 
	$dumpfile("W4P1B_tb.vcd");
	$dumpvars(0,W4P1B_tb);
	
	a=0;b=0;cin=0;#20;
	a=0;b=0;cin=1;#20;
	a=0;b=1;cin=0;#20;
	a=0;b=1;cin=1;#20;
	a=1;b=0;cin=0;#20;
	a=1;b=0;cin=1;#20;
	a=1;b=1;cin=0;#20;
	a=1;b=1;cin=1;#20;
	
	$display("Test Complete");
	
end 
endmodule

DSD/WEEK4/W4P1B_tb.vcd
$date
	Thu Sep 15 09:30:56 2022
$end
$version
	Icarus Verilog
$end
$timescale
	1ns
$end
$scope module W4P1B_tb $end
$var wire 1 ! s $end
$var wire 1 " cout $end
$var reg 1 # a $end
$var reg 1 $ b $end
$var reg 1 % cin $end
$scope module fa $end
$var wire 1 # a $end
$var wire 1 $ b $end
$var wire 1 % cin $end
$var wire 1 " cout $end
$var wire 1 ! s $end
$upscope $end
$upscope $end
$enddefinitions $end
#0
$dumpvars
0%
0$
0#
0"
0!
$end
#20
1!
1%
#40
0%
1$
#60
1"
0!
1%
#80
0"
1!
0%
0$
1#
#100
1"
0!
1%
#120
0%
1$
#140
1!
1%
