4.DSD/WEEK2/W2P1B.v
module W2P1B(a,b,c,d,f);
input a,b,c,d;
output f;
and(k1,~b,c);
and(k2,d,~b);
and(k3,~c,~d);
and(k4,k3,b);
or(k5,k1,k2);
or(f,k4,k5);
endmodule

4.DSD/WEEK2/W2P1B_tb.v
`timescale 1ns/1ns
`include "W2P1B.v"
module W2P1B_tb;
reg a,b,c,d;
wire f;
W2P1B uut(a,b,c,d,f);
initial begin
        $dumpfile("W2P1B_tb.vcd");
        $dumpvars(0,W2P1B_tb);
             
        a=0;
        b=0;
        c=0;
        d=0;
        #20;
             
        a=0;
        b=0;
        c=0;
        d=1;
        #20;
             
        a=0;
        b=0;
        c=1;
        d=0;
        #20;
             
        a=0;
        b=0;
        c=1;
        d=1;
        #20;
        
        a=0;
        b=1;
        c=0;
        d=0;
        #20;
        
        a=0;
        b=1;
        c=0;
        d=1;
        #20;
             
        a=0;
        b=1;
        c=1;
        d=0;
        #20;
             
        a=0;
        b=1;
        c=1;
        d=1;
        #20;
        
        a=1;
        b=0;
        c=0;
        d=0;
        #20;
        
        a=1;
        b=0;
        c=0;
        d=1;
        #20;
        
        a=1;
        b=0;
        c=1;
        d=0;
        #20;
        
        a=1;
        b=0;
        c=1;
        d=1;
        #20;
        
        a=1;
        b=1;
        c=0;
        d=0;
        #20;
        
        a=1;
        b=1;
        c=0;
        d=1;
        #20;
        
        a=1;
        b=1;
        c=1;
        d=0;
        #20;
        
        a=1;
        b=1;
        c=1;
        d=1;
        #20;
             
             
        $display("Test Complete");
end
endmodule

DSD/WEEK2/W2P1B_tb.vcd
$date
	Thu Sep  8 10:26:16 2022
$end
$version
	Icarus Verilog
$end
$timescale
	1ns
$end
$scope module W2P1B_tb $end
$var wire 1 ! f $end
$var reg 1 " a $end
$var reg 1 # b $end
$var reg 1 $ c $end
$var reg 1 % d $end
$scope module uut $end
$var wire 1 " a $end
$var wire 1 # b $end
$var wire 1 $ c $end
$var wire 1 % d $end
$var wire 1 ! f $end
$var wire 1 & k1 $end
$var wire 1 ' k2 $end
$var wire 1 ( k3 $end
$var wire 1 ) k4 $end
$var wire 1 * k5 $end
$upscope $end
$upscope $end
$enddefinitions $end
#0
$dumpvars
0*
0)
1(
0'
0&
0%
0$
0#
0"
0!
$end
#20
1!
1*
0(
1'
1%
#40
0'
1&
0%
1$
#60
1'
1%
#80
1)
0*
1(
0'
0&
0%
0$
1#
#100
0!
0)
0(
1%
#120
0%
1$
#140
1%
#160
1(
0%
0$
0#
1"
#180
1!
1*
0(
1'
1%
#200
0'
1&
0%
1$
#220
1'
1%
#240
1)
0*
1(
0'
0&
0%
0$
1#
#260
0!
0)
0(
1%
#280
0%
1$
#300
1%
