DSD/WEEK2/W2P2B.v
module W2P2B(a,b,c,d,f);
input a,b,c,d;
output f;
or(k1,c,d);
or(k2,k1,~b);
or(k3,~d,c);
or(k4,k3,~a);
or(k5,b,~a);
or(k6,k5,~c);
or(k7,a,~c);
or(k8,k7,~b);
and(k9,k2,k4);
and(k10,k6,k8);
and(f,k9,k10);
endmodule

DSD/WEEK2/W2P2B_tb.v
`timescale 1ns/1ns
`include "W2P2B.v"
module W2P2B_tb;
reg a,b,c,d;
wire f;
W2P2B uut(a,b,c,d,f);
initial begin
        $dumpfile("W2P2B_tb.vcd");
        $dumpvars(0,W2P2B_tb);
             
        a=0;
        b=0;
        c=0;
        d=0;
        #20;
             
        a=0;
        b=0;
        c=0;
        d=1;
        #20;
             
        a=0;
        b=0;
        c=1;
        d=0;
        #20;
             
        a=0;
        b=0;
        c=1;
        d=1;
        #20;
        
        a=0;
        b=1;
        c=0;
        d=0;
        #20;
        
        a=0;
        b=1;
        c=0;
        d=1;
        #20;
             
        a=0;
        b=1;
        c=1;
        d=0;
        #20;
             
        a=0;
        b=1;
        c=1;
        d=1;
        #20;
        
        a=1;
        b=0;
        c=0;
        d=0;
        #20;
        
        a=1;
        b=0;
        c=0;
        d=1;
        #20;
        
        a=1;
        b=0;
        c=1;
        d=0;
        #20;
        
        a=1;
        b=0;
        c=1;
        d=1;
        #20;
        
        a=1;
        b=1;
        c=0;
        d=0;
        #20;
        
        a=1;
        b=1;
        c=0;
        d=1;
        #20;
        
        a=1;
        b=1;
        c=1;
        d=0;
        #20;
        
        a=1;
        b=1;
        c=1;
        d=1;
        #20;
             
             
        $display("Test Complete");
end
endmodule

DSD/WEEK2/W2P2B_tb.vcd
$date
	Thu Sep  8 10:28:43 2022
$end
$version
	Icarus Verilog
$end
$timescale
	1ns
$end
$scope module W2P2B_tb $end
$var wire 1 ! f $end
$var reg 1 " a $end
$var reg 1 # b $end
$var reg 1 $ c $end
$var reg 1 % d $end
$scope module uut $end
$var wire 1 " a $end
$var wire 1 # b $end
$var wire 1 $ c $end
$var wire 1 % d $end
$var wire 1 ! f $end
$var wire 1 & k1 $end
$var wire 1 ' k10 $end
$var wire 1 ( k2 $end
$var wire 1 ) k3 $end
$var wire 1 * k4 $end
$var wire 1 + k5 $end
$var wire 1 , k6 $end
$var wire 1 - k7 $end
$var wire 1 . k8 $end
$var wire 1 / k9 $end
$upscope $end
$upscope $end
$enddefinitions $end
#0
$dumpvars
1/
1.
1-
1,
1+
1*
1)
1(
1'
0&
0%
0$
0#
0"
1!
$end
#20
0)
1&
1%
#40
0-
1)
0%
1$
#60
1%
#80
0!
0/
1'
1-
0(
1.
0&
1)
0%
0$
1#
#100
1!
1/
1(
0)
1&
1%
#120
0!
0'
0.
0-
1)
0%
1$
#140
1%
#160
1!
1/
1'
1*
1.
0&
1)
0+
1-
0%
0$
0#
1"
#180
0!
0/
0*
0)
1&
1%
#200
1/
0'
1*
0,
1)
0%
1$
#220
1%
#240
0/
1'
1*
0(
1,
0&
1)
1+
0%
0$
1#
#260
0*
1(
0)
1&
1%
#280
1!
1/
1*
1)
0%
1$
#300
1%
