4.DSD/WEEK2/W2P2A.v
module W2P2A(a,b,c,d,f);
input a,b,c,d;
output f;
or(k1,c,b);
or(k2,~b,d);
and(f,k1,k2);
endmodule

DSD/WEEK2/W2P2A_tb.v
`timescale 1ns/1ns
`include "W2P2A.v"
module W2P2A_tb;
reg a,b,c,d;
wire f;
W2P2A uut(a,b,c,d,f);
initial begin
        $dumpfile("W2P2A_tb.vcd");
        $dumpvars(0,W2P2A_tb);
             
        a=0;
        b=0;
        c=0;
        d=0;
        #20;
             
        a=0;
        b=0;
        c=0;
        d=1;
        #20;
             
        a=0;
        b=0;
        c=1;
        d=0;
        #20;
             
        a=0;
        b=0;
        c=1;
        d=1;
        #20;
        
        a=0;
        b=1;
        c=0;
        d=0;
        #20;
        
        a=0;
        b=1;
        c=0;
        d=1;
        #20;
             
        a=0;
        b=1;
        c=1;
        d=0;
        #20;
             
        a=0;
        b=1;
        c=1;
        d=1;
        #20;
        
        a=1;
        b=0;
        c=0;
        d=0;
        #20;
        
        a=1;
        b=0;
        c=0;
        d=1;
        #20;
        
        a=1;
        b=0;
        c=1;
        d=0;
        #20;
        
        a=1;
        b=0;
        c=1;
        d=1;
        #20;
        
        a=1;
        b=1;
        c=0;
        d=0;
        #20;
        
        a=1;
        b=1;
        c=0;
        d=1;
        #20;
        
        a=1;
        b=1;
        c=1;
        d=0;
        #20;
        
        a=1;
        b=1;
        c=1;
        d=1;
        #20;
             
             
        $display("Test Complete");
end
endmodule

DSD/WEEK2/W2P2A_tb.vcd
$date
	Thu Sep  8 10:27:56 2022
$end
$version
	Icarus Verilog
$end
$timescale
	1ns
$end
$scope module W2P2A_tb $end
$var wire 1 ! f $end
$var reg 1 " a $end
$var reg 1 # b $end
$var reg 1 $ c $end
$var reg 1 % d $end
$scope module uut $end
$var wire 1 " a $end
$var wire 1 # b $end
$var wire 1 $ c $end
$var wire 1 % d $end
$var wire 1 ! f $end
$var wire 1 & k1 $end
$var wire 1 ' k2 $end
$upscope $end
$upscope $end
$enddefinitions $end
#0
$dumpvars
1'
0&
0%
0$
0#
0"
0!
$end
#20
1%
#40
1!
1&
0%
1$
#60
1%
#80
0!
0'
0%
0$
1#
#100
1!
1'
1%
#120
0!
0'
0%
1$
#140
1!
1'
1%
#160
0!
0&
0%
0$
0#
1"
#180
1%
#200
1!
1&
0%
1$
#220
1%
#240
0!
0'
0%
0$
1#
#260
1!
1'
1%
#280
0!
0'
0%
1$
#300
1!
1'
1%
